LICENSE
README.md
pyproject.toml
setup.py
ua_alarm/__init__.py
ua_alarm/client.py
ua_alarm.egg-info/PKG-INFO
ua_alarm.egg-info/SOURCES.txt
ua_alarm.egg-info/dependency_links.txt
ua_alarm.egg-info/requires.txt
ua_alarm.egg-info/top_level.txt
ua_alarm/enums/__init__.py
ua_alarm/enums/alert_type.py
ua_alarm/enums/v2_region_type.py
ua_alarm/types/__init__.py
ua_alarm/types/alert.py
ua_alarm/types/alert_modification.py
ua_alarm/types/alert_region_model.py
ua_alarm/types/region_alarm_model.py
ua_alarm/types/region_alarms_history.py
ua_alarm/types/region_view_model.py
ua_alarm/types/regions_view_model.py
ua_alarm/types/time_span.py
ua_alarm/types/web_hook.py